excel_agent/__init__.py
excel_agent/agent_runner.py
excel_agent/config.py
excel_agent/reasoning_models.py
excel_mcp/__init__.py
excel_mcp/errors.py
excel_mcp/excel_server.py
excel_mcp/formatting.py
excel_mcp/helpers.py
excel_mcp/models.py
excel_mcp/schemas.py
excel_mcp/sessions.py
iflow_mcp_sylvianai_excel_agent-0.1.1.dist-info/licenses/LICENSE
iflow_mcp_sylvianai_excel_agent-0.1.1.dist-info/METADATA
iflow_mcp_sylvianai_excel_agent-0.1.1.dist-info/WHEEL
iflow_mcp_sylvianai_excel_agent-0.1.1.dist-info/entry_points.txt
iflow_mcp_sylvianai_excel_agent-0.1.1.dist-info/top_level.txt
iflow_mcp_sylvianai_excel_agent-0.1.1.dist-info/RECORD
