Metadata-Version: 2.4
Name: iflow-mcp_sylvianai_excel-agent
Version: 0.1.1
Summary: Excel Agent with MCP server
Requires-Python: >=3.10
License-File: LICENSE
Requires-Dist: openpyxl>=3.1.0
Requires-Dist: pydantic>=2.0.0
Requires-Dist: fastmcp>=2.0.0
Dynamic: license-file
